flatten_list/__init__.py
flatten_list/flatten_list.py
flatten_list-0.2.0.dist-info/DESCRIPTION.rst
flatten_list-0.2.0.dist-info/METADATA
flatten_list-0.2.0.dist-info/RECORD
flatten_list-0.2.0.dist-info/WHEEL
flatten_list-0.2.0.dist-info/metadata.json
flatten_list-0.2.0.dist-info/top_level.txt
